{
	"info": {
		"_postman_id": "d591e741-4901-4b19-84a0-3e2830c28bdc",
		"name": "clients-service",
		"schema": "https://schema.getpostman.com/json/collection/v2.1.0/collection.json"
	},
	"item": [
		{
			"name": "delete",
			"request": {
				"method": "DELETE",
				"header": [],
				"url": {
					"raw": "https://kx72g7yl59.execute-api.us-west-2.amazonaws.com/dev/clients/b628d660-c77b-457f-86eb-c45bb976fa01",
					"protocol": "https",
					"host": [
						"kx72g7yl59",
						"execute-api",
						"us-west-2",
						"amazonaws",
						"com"
					],
					"path": [
						"dev",
						"clients",
						"b628d660-c77b-457f-86eb-c45bb976fa01"
					]
				}
			},
			"response": []
		},
		{
			"name": "list",
			"request": {
				"method": "GET",
				"header": [],
				"url": {
					"raw": "https://9g908trvva.execute-api.us-west-2.amazonaws.com/6532/clients?subscriber_uuid=adda9a1f-98f1-4ce2-ba4a-372f0dc32f51",
					"protocol": "https",
					"host": [
						"9g908trvva",
						"execute-api",
						"us-west-2",
						"amazonaws",
						"com"
					],
					"path": [
						"6532",
						"clients"
					],
					"query": [
						{
							"key": "subscriber_uuid",
							"value": "adda9a1f-98f1-4ce2-ba4a-372f0dc32f51"
						}
					]
				}
			},
			"response": []
		},
		{
			"name": "show",
			"request": {
				"method": "GET",
				"header": [],
				"url": {
					"raw": "https://9g908trvva.execute-api.us-west-2.amazonaws.com/6532/clients/c4cc4f20-416a-4cdf-85b1-5caa4b4ec1bb",
					"protocol": "https",
					"host": [
						"9g908trvva",
						"execute-api",
						"us-west-2",
						"amazonaws",
						"com"
					],
					"path": [
						"6532",
						"clients",
						"c4cc4f20-416a-4cdf-85b1-5caa4b4ec1bb"
					]
				}
			},
			"response": []
		},
		{
			"name": "delete",
			"request": {
				"method": "DELETE",
				"header": [],
				"url": {
					"raw": "https://9g908trvva.execute-api.us-west-2.amazonaws.com/6532/clients/c4cc4f20-416a-4cdf-85b1-5caa4b4ec1bb",
					"protocol": "https",
					"host": [
						"9g908trvva",
						"execute-api",
						"us-west-2",
						"amazonaws",
						"com"
					],
					"path": [
						"6532",
						"clients",
						"c4cc4f20-416a-4cdf-85b1-5caa4b4ec1bb"
					]
				}
			},
			"response": []
		},
		{
			"name": "show-profile",
			"request": {
				"method": "GET",
				"header": [],
				"url": {
					"raw": "https://9g908trvva.execute-api.us-west-2.amazonaws.com/6532/clients/c4cc4f20-416a-4cdf-85b1-5caa4b4ec1bb/profile",
					"protocol": "https",
					"host": [
						"9g908trvva",
						"execute-api",
						"us-west-2",
						"amazonaws",
						"com"
					],
					"path": [
						"6532",
						"clients",
						"c4cc4f20-416a-4cdf-85b1-5caa4b4ec1bb",
						"profile"
					]
				}
			},
			"response": []
		},
		{
			"name": "create",
			"request": {
				"method": "POST",
				"header": [],
				"body": {
					"mode": "raw",
					"raw": "{\n  \"first_name\": \"John\",\n  \"last_name\": \"Doe\",\n  \"middle_name\": \"Lennon\",\n  \"dob\": \"1980-10-09\",\n  \"email\": \"john@doe.com\",\n  \"current_user\": \"test user\",\n  \"height\": 1.90,\n  \"weight\": 210,\n  \"user_ref\": \"af7dcd26-736d-49fc-98b3-bce5aa5c36d3\",\n  \"subscriber_uuid\": \"adda9a1f-98f1-4ce2-ba4a-372f0dc32f51\",\n  \"location_uuid\": \"af7dcd26-736d-49fc-98b3-bce5aa5c36e5\",\n  \"ssn\": \"220-23-5602\",\n  \"ethnicity_id\": 1,\n  \"marital_status_id\": 1,\n  \"drivers_license\": \"8447315\",\n  \"lives_with\": \"friend\",\n  \"employment\": \"Intern\",\n  \"education_completed\": \"Bachelor's Degree\",\n  \"address_attributes\": {\n    \"address_line_1\": \"Block Block\",\n    \"address_line_2\": \"68254\",\n    \"city\": \"Paranaque\",\n    \"state\": \"MM\",\n    \"postcode\": \"8107\",\n    \"is_primary\": true,\n    \"current_user\": \"Peter Parker\"\n  },\n  \"contacts_attributes\": [\n    {\n      \"last_name\": \"Juan\",\n      \"middle_name\": \"Agustin\",\n      \"first_name\": \"Dela Cruz\",\n      \"contact_type\": 1,\n      \"relationship\": \"Father\",\n      \"email\": \"test13234@example.com\",\n      \"current_user\": \"Mary Watson\",\n      \"phone_contacts_attributes\": [\n      {\n        \"ordinality\": 1,\n        \"phone_type\": \"home\",\n        \"phone_number\": \"+41345678901\",\n        \"phone_extension\": \"123\",\n        \"not_okay_to_leave_message\": false,\n        \"current_user\": \"test\"\n      },\n      {\n        \"ordinality\": 2,\n        \"phone_type\": \"mobile\",\n        \"phone_number\": \"+42345678901\",\n        \"phone_extension\": \"456\",\n        \"not_okay_to_leave_message\": false,\n        \"current_user\": \"test\"\n      }],\n      \"address_attributes\": {\n        \"address_line_1\": \"San Roque\",\n        \"address_line_2\": \"45678\",\n        \"city\": \"Pasay\",\n        \"state\": \"MM\",\n        \"postcode\": \"1303\",\n        \"is_primary\": true,\n        \"current_user\": \"Peter Parker\"\n      }\n    },\n    {\n      \"last_name\": \"Jane\",\n      \"middle_name\": \"Ramos\",\n      \"first_name\": \"Dela Cruz\",\n      \"contact_type\": 2,\n      \"relationship\": \"Mother\",\n      \"email\": \"test13234@example.com\",\n      \"current_user\": \"Mary Watson\",\n      \"address_attributes\": {\n        \"address_line_1\": \"San Vicente\",\n        \"address_line_2\": \"69874\",\n        \"city\": \"Las Pinas\",\n        \"state\": \"MM\",\n        \"postcode\": \"1907\",\n        \"is_primary\": true,\n        \"current_user\": \"Peter Parker\"\n      }\n    }\n  ],\n  \"phone_contacts_attributes\": [\n    {\n      \"ordinality\": 1,\n      \"phone_type\": \"home\",\n      \"phone_number\": \"+12345678901\",\n      \"phone_extension\": \"123\",\n      \"not_okay_to_leave_message\": false,\n      \"current_user\": \"test\"\n    },\n    {\n      \"ordinality\": 2,\n      \"phone_type\": \"mobile\",\n      \"phone_number\": \"+12345678901\",\n      \"phone_extension\": \"456\",\n      \"not_okay_to_leave_message\": false,\n      \"current_user\": \"test\"\n    },\n    {\n      \"ordinality\": 3,\n      \"phone_type\": \"office\",\n      \"phone_number\": \"+12345678901\",\n      \"phone_extension\": \"456\",\n      \"not_okay_to_leave_message\": false,\n      \"current_user\": \"test\"\n    }\n  ],\n  \"children_attributes\": [\n    {\n      \"last_name\": \"Jordan\",\n      \"first_name\": \"Michael\",\n      \"middle_name\": \"J\",\n      \"gender\": \"male\",\n      \"relationship\": \"son\",\n      \"lives_with\": \"father\",\n      \"email\": \"mj@example.com\",\n      \"current_user\": \"Mary Watson\",\n      \"address_attributes\": {\n        \"address_line_1\": \"San Dionisio\",\n        \"address_line_2\": \"68254\",\n        \"city\": \"Makati\",\n        \"state\": \"MM\",\n        \"postcode\": \"8107\",\n        \"is_primary\": true,\n        \"current_user\": \"Peter Parker\"\n      }\n    },\n    {\n      \"last_name\": \"Byant\",\n      \"first_name\": \"Kobe\",\n      \"middle_name\": \"J\",\n      \"gender\": \"male\",\n      \"relationship\": \"son\",\n      \"lives_with\": \"father\",\n      \"email\": \"kb@example.com\",\n      \"current_user\": \"Gwen Stacy\",\n      \"address_attributes\": {\n        \"address_line_1\": \"Block 9\",\n        \"address_line_2\": \"68254\",\n        \"city\": \"Pasig\",\n        \"state\": \"MM\",\n        \"postcode\": \"8107\",\n        \"is_primary\": true,\n        \"current_user\": \"Peter Parker\"\n      }\n    }\n  ]\n}",
					"options": {
						"raw": {
							"language": "json"
						}
					}
				},
				"url": {
					"raw": "https://9g908trvva.execute-api.us-west-2.amazonaws.com/6532/clients/",
					"protocol": "https",
					"host": [
						"9g908trvva",
						"execute-api",
						"us-west-2",
						"amazonaws",
						"com"
					],
					"path": [
						"6532",
						"clients",
						""
					]
				}
			},
			"response": []
		},
		{
			"name": "update",
			"request": {
				"method": "PUT",
				"header": [],
				"body": {
					"mode": "raw",
					"raw": "{\n  \"drivers_license\": \"844731235\",\n  \"current_user\": \"Peter Parker\",\n  \"address_attributes\": {\n    \"address_line_2\": \"6825423\"\n  },\n  \"contacts_attributes\": [\n    {\n      \"last_name\": \"Juan\",\n      \"middle_name\": \"Agustin\",\n      \"first_name\": \"Dela Cruz\",\n      \"contact_type\": 1,\n      \"relationship\": \"Father\",\n      \"email\": \"test13234@example.com\",\n      \"current_user\": \"Mary Watson\",\n      \"phone_contacts_attributes\": [\n      {\n        \"ordinality\": 1,\n        \"phone_type\": \"home\",\n        \"phone_number\": \"+41345678901\",\n        \"phone_extension\": \"123\",\n        \"not_okay_to_leave_message\": false,\n        \"current_user\": \"test\"\n      },\n      {\n        \"ordinality\": 2,\n        \"phone_type\": \"mobile\",\n        \"phone_number\": \"+42345678901\",\n        \"phone_extension\": \"456\",\n        \"not_okay_to_leave_message\": false,\n        \"current_user\": \"test\"\n      }],\n      \"address_attributes\": {\n        \"address_line_1\": \"San Roque\",\n        \"address_line_2\": \"45678\",\n        \"city\": \"Pasay\",\n        \"state\": \"MM\",\n        \"postcode\": \"1303\",\n        \"is_primary\": true,\n        \"current_user\": \"Peter Parker\"\n      }\n    },\n    {\n      \"last_name\": \"Jane\",\n      \"middle_name\": \"Ramos\",\n      \"first_name\": \"Dela Cruz\",\n      \"contact_type\": 2,\n      \"relationship\": \"Mother\",\n      \"email\": \"test13234@example.com\",\n      \"current_user\": \"Mary Watson\",\n      \"address_attributes\": {\n        \"address_line_1\": \"San Vicente\",\n        \"address_line_2\": \"69874\",\n        \"city\": \"Las Pinas\",\n        \"state\": \"MM\",\n        \"postcode\": \"1907\",\n        \"is_primary\": true,\n        \"current_user\": \"Peter Parker\"\n      }\n    }\n  ],\n  \"phone_contacts_attributes\": [\n    {\n      \"ordinality\": 1,\n      \"phone_type\": \"home\",\n      \"phone_number\": \"+12345678901\",\n      \"phone_extension\": \"123\",\n      \"not_okay_to_leave_message\": false,\n      \"current_user\": \"test\"\n    },\n    {\n      \"ordinality\": 2,\n      \"phone_type\": \"mobile\",\n      \"phone_number\": \"+12345678901\",\n      \"phone_extension\": \"456\",\n      \"not_okay_to_leave_message\": false,\n      \"current_user\": \"test\"\n    },\n    {\n      \"ordinality\": 3,\n      \"phone_type\": \"office\",\n      \"phone_number\": \"+12345678901\",\n      \"phone_extension\": \"456\",\n      \"not_okay_to_leave_message\": false,\n      \"current_user\": \"test\"\n    }\n  ],\n  \"children_attributes\": [\n    {\n      \"last_name\": \"Jordan\",\n      \"first_name\": \"Michael\",\n      \"middle_name\": \"J\",\n      \"gender\": \"male\",\n      \"relationship\": \"son\",\n      \"lives_with\": \"father\",\n      \"email\": \"mj@example.com\",\n      \"current_user\": \"Mary Watson\",\n      \"address_attributes\": {\n        \"address_line_1\": \"San Dionisio\",\n        \"address_line_2\": \"68254\",\n        \"city\": \"Makati\",\n        \"state\": \"MM\",\n        \"postcode\": \"8107\",\n        \"is_primary\": true,\n        \"current_user\": \"Peter Parker\"\n      }\n    },\n    {\n      \"last_name\": \"Byant\",\n      \"first_name\": \"Kobe\",\n      \"middle_name\": \"J\",\n      \"gender\": \"male\",\n      \"relationship\": \"son\",\n      \"lives_with\": \"father\",\n      \"email\": \"kb@example.com\",\n      \"current_user\": \"Gwen Stacy\",\n      \"address_attributes\": {\n        \"address_line_1\": \"Block 9\",\n        \"address_line_2\": \"68254\",\n        \"city\": \"Pasig\",\n        \"state\": \"MM\",\n        \"postcode\": \"8107\",\n        \"is_primary\": true,\n        \"current_user\": \"Peter Parker\"\n      }\n    }\n  ]\n}",
					"options": {
						"raw": {
							"language": "json"
						}
					}
				},
				"url": {
					"raw": "https://9g908trvva.execute-api.us-west-2.amazonaws.com/6532/clients/a8d077d1-88d9-41e8-bbe8-b523671b4ac4",
					"protocol": "https",
					"host": [
						"9g908trvva",
						"execute-api",
						"us-west-2",
						"amazonaws",
						"com"
					],
					"path": [
						"6532",
						"clients",
						"a8d077d1-88d9-41e8-bbe8-b523671b4ac4"
					]
				}
			},
			"response": []
		}
	],
	"protocolProfileBehavior": {}
}